LICENSE.txt
MANIFEST.in
README.rst
setup.py
distutils_ui/__init__.py
distutils_ui/build_ui.py
distutils_ui.egg-info/PKG-INFO
distutils_ui.egg-info/SOURCES.txt
distutils_ui.egg-info/dependency_links.txt
distutils_ui.egg-info/top_level.txt
example/setup.cfg.py2qt4
example/setup.cfg.py3qt4
example/setup.cfg.pyqt5
example/setup.py
example/example/example-pyqt4.py
example/example/example-pyqt5.py
example/example/i18n/example_de.ts
example/example/images/icon.png
example/example/ui/__init__.py
example/example/ui/dialog.ui