Metadata-Version: 1.1
Name: distutils-ui
Version: 0.1.2
Summary: A distutils build extension for PyQt{4,5} applications
Home-page: https://github.com/frispete/distutils_ui
Author: Hans-Peter Jansen
Author-email: hpj@urpla.net
License: MIT
Keywords: distutils setuptools generate translate build resources
Platform: UNKNOWN
Classifier: Development Status :: 5 - Production/Stable
Classifier: Framework :: Setuptools Plugin
Classifier: Environment :: Console
Classifier: Environment :: MacOS X
Classifier: Environment :: Win32 (MS Windows)
Classifier: Environment :: X11 Applications :: Qt
Classifier: Intended Audience :: Developers
Classifier: License :: OSI Approved :: MIT License
Classifier: Natural Language :: English
Classifier: Operating System :: MacOS :: MacOS X
Classifier: Operating System :: Microsoft :: Windows
Classifier: Operating System :: POSIX
Classifier: Programming Language :: Python :: 2
Classifier: Programming Language :: Python :: 3
Classifier: Topic :: Software Development
Classifier: Topic :: Software Development :: Build Tools
Classifier: Topic :: Software Development :: Internationalization
Classifier: Topic :: Software Development :: Localization
Classifier: Topic :: Software Development :: User Interfaces
Classifier: Topic :: System :: Software Distribution
